UseMod/Box.py
UseMod/Dropbox.py
UseMod/Github.py
UseMod/__init__.py
UseMod/assets/Delete.ico
UseMod/assets/Info.ico
UseMod-1.1.1.dist-info/LICENSE
UseMod-1.1.1.dist-info/METADATA
UseMod-1.1.1.dist-info/WHEEL
UseMod-1.1.1.dist-info/top_level.txt
UseMod-1.1.1.dist-info/RECORD
