Metadata-Version: 2.1
Name: UseMod
Version: 1.1.1
Summary: UseMod
Home-page: https://github.com/Grivy16/UseMod/wiki
Author: Grivy16
Author-email: grivy16public@gmail.com
Classifier: Programming Language :: Python :: 3
Classifier: License :: OSI Approved :: MIT License
Classifier: Operating System :: OS Independent
Requires-Python: >=3.6
License-File: LICENSE
Requires-Dist: requests
Requires-Dist: dropbox
Requires-Dist: clipboard
Requires-Dist: customtkinter
Requires-Dist: Pillow
